{"walls":[
[
  {"x":30, "y":650},
  {"x":140, "y":650},
  {"x":150, "y":660},
  {"x":670, "y":660},
  {"x":680, "y":650},
  {"x":870, "y":650},
  {"x":870, "y":580},
  {"x":190, "y":580},
  {"x":190, "y":570},
  {"x":870, "y":570},
  {"x":870, "y":500},
  {"x":750, "y":500},
  {"x":750, "y":490},
  {"x":870, "y":490},
  {"x":870, "y":420},
  {"x":420, "y":420},
  {"x":420, "y":410},
  {"x":870, "y":410},
  {"x":870, "y":330},
  {"x":820, "y":330},
  {"x":820, "y":320},
  {"x":870, "y":320},
  {"x":870, "y":260},
  {"x":200, "y":260},
  {"x":200, "y":250},
  {"x":870, "y":250},
  {"x":870, "y":180},
  {"x":600, "y":180},
  {"x":600, "y":170},
  {"x":870, "y":170},
  {"x":870, "y":20},
  {"x":20, "y":20},
  {"x":20, "y":160},
  {"x":500, "y":160},
  {"x":500, "y":170},
  {"x":20, "y":170},
  {"x":20, "y":240},
  {"x":120, "y":240},
  {"x":120, "y":270},
  {"x":20, "y":270},
  {"x":20, "y":330},
  {"x":730, "y":330},
  {"x":730, "y":350},
  {"x":690, "y":350},
  {"x":690, "y":340},
  {"x":20, "y":340},
  {"x":20, "y":410},
  {"x":340, "y":410},
  {"x":340, "y":430},
  {"x":20, "y":430},
  {"x":20, "y":500},
  {"x":90, "y":500},
  {"x":90, "y":490},
  {"x":660, "y":490},
  {"x":660, "y":500},
  {"x":110, "y":500},
  {"x":110, "y":510},
  {"x":40, "y":510},
  {"x":40, "y":570},
  {"x":130, "y":570},
  {"x":130, "y":580},
  {"x":120, "y":590},
  {"x":30, "y":590},
  {"x":30, "y":630}
],
[
  {"x":80, "y":70},
  {"x":200, "y":120},
  {"x":320, "y":70},
  {"x":400, "y":110},
  {"x":540, "y":60},
  {"x":670, "y":120},
  {"x":720, "y":90},
  {"x":780, "y":110},
  {"x":790, "y":100},
  {"x":720, "y":70},
  {"x":660, "y":100},
  {"x":530, "y":50},
  {"x":400, "y":90},
  {"x":320, "y":60},
  {"x":200, "y":110},
  {"x":80, "y":60}
]  
],

"holes":[
[
  {"x":840, "y":330},
  {"x":870, "y":330},
  {"x":870, "y":410},
  {"x":840, "y":410},
  {"x":840, "y":370}
],
[
  {"x":60, "y":230},
  {"x":60, "y":170},
  {"x":20, "y":170},
  {"x":20, "y":240},
  {"x":60, "y":240}
],
[
  {"x":30, "y":590},
  {"x":30, "y":650},
  {"x":110, "y":650},
  {"x":70, "y":590}
],
[
  {"x":660, "y":480},
  {"x":660, "y":510},
  {"x":680, "y":510},
  {"x":680, "y":480}
]
],

"checkpoints":[
  {"x":820, "y":610},
  {"x":550, "y":610},
  {"x":120, "y":620},
  {"x":60, "y":540},
  {"x":420, "y":510},
  {"x":840, "y":540},
  {"x":830, "y":450},
  {"x":480, "y":460},
  {"x":50, "y":460},
  {"x":90, "y":360},
  {"x":550, "y":380},
  {"x":800, "y":380},
  {"x":820, "y":290},
  {"x":510, "y":310},
  {"x":240, "y":280},
  {"x":50, "y":310},
  {"x":250, "y":200},
  {"x":90, "y":210},
  {"x":660, "y":220},
  {"x":850, "y":210},
  {"x":720, "y":120},
  {"x":530, "y":90},
  {"x":320, "y":100},
  {"x":420, "y":60},
  {"x":660, "y":70},
  {"x":190, "y":50},
  {"x":40, "y":130},
  {"x":840, "y":40}
]
}